Workbook

Sheet Conservative
A1: Walmart Frontline AI Tranforamtion (Included store operations, customer service, workforce management and inventory management etc)
A2: Probability of Occurrence | C2: Financial Impact | D2: Operational Impact | E2: Competitive Impact | F2: Reputational Impact | G2: Techinal Impact | H2: Legal / Compliance Impact
A3: Very Unlikely | B3: 1 | C3: Financial loss < $1M | D3: Minimal operational disruption | E3: No measurable competitive impact | F3: Internal avareness only | G3: Minor technical issure | H3: Minor policy violation
A4: Somewhat unlikely | B4: 3 | C4: Financial loss between $1M - $10M | D4: Single store disruption | E4: Minor market share loss | F4: Limited custoemr complaints | G4: Temporary service degradation | H4: Internal compliance issue
A5: 50-50 possibility | B5: 5 | C5: Financial loss between $10M - $50M | D5: Mutliple stores affected | E5: Noticebal local/ regional competitive disadvantage | F5: Regional negative publicity | G5: Store-level system disruption | H5: Regulatory inquiry
A6: Somewhat likely | B6: 7 | C6: Financial loss between $50M - $100M | D6: Regional operational disruption | E6: Significant customer migration to competitors | F6: National media coverage | G6: Multi-region technology outage | H6: Investigation and penalties
A7: Very likely | B7: 9 | C7: Financial loss > $100M | D7: Entreprise-wide operational disruption | E7: Strategic loss of competitive position | F7: Long-term brand damage and trust erosion | G7: Entrepise-wide technology failure | H7: Major fines, Litigation or regulatory sanctions
A11: Impact of Risk : defined as the impact to the firm before the controls. (Inherent risk) | C11: Financial: Possibility of a significant monetary loss or gain | D11: Operational | E11: Competitive Risks: Some competitors in the industry might hurt the company's business. Pick hospitals that are closed to competitors' health center, count the total admissions change rates in these hospitals. | F11: Reputational: May impact the company brand or standing associated with a positive or negative incident/issue | G11: Technical | H11: Legal/Compliance
A12: Very Low | B12: 1 | C12: Expected labor cost reduction not achieved
A13: Somewhat Low | B13: 2 | C13: AI implementation cost overrun | D13: Productivity decline during transition | F13: AI-related customer compaints | G13: AI model drift
A14: Moderate | B14: 4 | C14: Inventory loss from AI forecast errors | D14: Incorrect workforce scheduling | E14: Faster AI adoption by Competitors | F14: Negative publice preception of AI | G14: AI recommedndation inaccuracy | H14: Algorithmic Bias and Ethical AI issues
D15: Poor data quality
D16: operational decision errors
A17: Somewhat High | B17: 6 | C17: Revenue loss from AI service disruptions | D17: Overstock risk | E17: Customer migration to competitors | F17: Customer trust erosion | G17: Legacy system intergration failure | H17: Regulatory Non-compliance
D18: Replenishment delay | G18: Vendor dependency
D19: excessive dependence on automation
A20: High | B20: 8 | C20: ROI realization failure | D20: Inventory forecast error | E20: Competitve AI disruption | F20: Brand damage from AI failures | G20: System Downtime | H20: Customer Data Breach
D21: Stockout risk
D22: Fulfillment disruption
A23: Extremely High | B23: 9

Sheet Risk Log
A1: Risk # | B1: Risk Category name | C1: Date | D1: The Risk of/That | E1: Caused by | F1: Resulting In | G1: Consequence/Impact | H1: Likelihood Score | I1: Impact Score | J1: Risk Score | K1: Priority (H, M, L) | L1: Mitigation | M1: Risk Owner | N1: Open/Closed
A2: R-001 | B2: Competitive AI Disruption | C2: 46174 | D2: The risk of market share erosion in AI-enabled retail categories | E2: Caused by rapid AI capability development by Amazon, Target, and AI-native competitors who have established AI-first operations ahead of Walmart | F2: Resulting in reduced customer retention, declining e-commerce market share by an estimated 3-5 percentage points, and revenue losses of $8-12 billion annually | G2: FINANCIAL: Revenue decline of $8-12B annually OPERATIONAL: Loss of competitive positioning in AI-enabled categories STRATEGIC: Diminished brand relevance among digital-native consumers TECHNOLOGY: Expanding AI capability gap versus Amazon and Target | H2: 3 | I2: 8 | J2: 24 | K2: H | L2: 1. Accelerate AI investment roadmap with $2B dedicated annual budget 2. Acquire AI-native startups to address the capability gap 3. Enhance Walmart+ subscription program with AI-personalized features and benefits 4. Deploy competitive intelligence monitoring system 5. Establish AI innovation laboratories | M2: Chief Strategy Officer / Chief AI Officer / R&D and Strategy department | N2: Open
A3: R-002 | B3: Customer Migration Risk | C3: 46174 | D3: The risk of customer attrition and loyalty erosion | E3: Caused by competitors offering superior AI-driven customer experiences, personalized recommendations, and digital engagement capabilities that Walmart has not yet fully replicated | F3: Resulting in reduced customer loyalty, declining retention rates, slower Walmart+ membership growth, and an estimated 4-7% customer churn increase | G3: FINANCIAL: Revenue loss from customer attrition estimated at $3-5B annually OPERATIONAL: Reduced transaction frequency and basket size REPUTATIONAL: Declining Net Promoter Score and brand preference TECHNOLOGY: Competitive disadvantage in AI personalization capabilities COMPLIANCE: Customer data privacy risks from expanded AI personalization | H3: 5 | I3: 6 | J3: 24 | K3: H | L3: 1. Deploy AI-powered personalization engine across Walmart.com and app 2. Invest in customer analytics and behavioral prediction models 3. Expand Walmart+ benefits with AI-curated recommendations 4. Implement real-time customer churn prediction and intervention program 5. Develop AI-powered digital engagement assistant for customer service | M3: Chief Customer Officer / VP Digital Experience / Compliance & Customer department | N3: Open
A4: R-003 | B4: AI-Driven Supply Chain Optimization and Cost Leadership Risk | C4: 46174 | D4: The risk/opportunity of capturing cost leadership advantage through AI-driven supply chain optimization | E4: Caused by successful implementation of AI forecasting, inventory optimization, and supply chain automation capabilities that competitors have not yet deployed at Walmart's scale | F4: Resulting in lower operating costs, improved inventory efficiency, enhanced competitive advantage, and incremental operating margin improvement of 1.5-2.5 percentage points | G4: FINANCIAL (POSITIVE): Operating margin improvement of $4-6B annually OPERATIONAL (POSITIVE): 20-30% reduction in inventory carrying costs STRATEGIC (POSITIVE): Sustainable cost leadership advantage over Amazon and Target TECHNOLOGY (POSITIVE): Monetization of AI infrastructure investment COMPETITIVE (POSITIVE): Faster replenishment and improved in-stock rates | H4: 5 | I4: 4 | J4: 16 | K4: H | L4: 1. Continue investment in AI-enabled supply chain technology and warehouse automation 2. Expand real-time IoT sensor deployment across 210+ distribution centers 3. Deploy AI demand forecasting models to reduce overstock and stockout events 4. Develop supplier collaboration platform with AI-driven order optimization 5. Establish supply chain AI Center of Excellence | M4: Chief Supply Chain Officer / VP Logistics Technology / Inventory & Technology department | N4: Open
A5: R-004 | B5: ROI realization failure | C5: 46181 | D5: The risk that Walmart fails to achieve the expected financial returns and operational benefits from Frontline AI Transformation investments. | E5: This risk may be caused by lower-than-expected employee adoption of AI tools, implementation delays across stores, insufficient process redesign, and overestimation of productivity improvements generated by AI-enabled operations. | F5: This may result in reduced operational savings, delayed realization of expected benefits, lower return on investment, and decreased confidence in future AI transformation initiatives. | G5: FINANCIAL: Failure to achieve projected AI benefits may reduce expected returns by an estimated $100M–$500M over the implementation lifecycle. OPERATIONAL: Reduced efficiency gains from workforce automation, inventory optimization, and AI-assisted decision-making. STRATEGIC: Reduced executive confidence in future AI investments and digital transformation programs. COMPETITIVE: Slower realization of AI benefits may widen the operational efficiency gap between Walmart and competitors such as Amazon and Target. | H5: 5 | I5: 8 | J5: =H5*I5 -> 40 | K5: H | L5: 1. Establish enterprise AI ROI monitoring dashboards. 2. Link AI initiatives to measurable business KPIs. 3. Conduct quarterly benefit realization reviews. 4. Implement phased deployment and pilot validation. 5. Establish executive AI governance oversight. | M5: Chief Financial Officer / Chief Technology Officer | N5: Open
A6: R-005 | B6: AI Implementation Cost Overrun | C6: 46181 | D6: The risk that Walmart's Frontline AI Transformation program exceeds approved implementation budgets and financial forecasts. | E6: This risk may be caused by project scope expansion, infrastructure upgrades, vendor cost increases, implementation complexity, consulting expenses, and unexpected integration requirements associated with legacy systems. | F6: This may result in budget overruns, reduced project profitability, delayed deployment schedules, and additional funding requirements. | G6: FINANCIAL: Additional implementation costs may exceed planned budgets by tens of millions of dollars. OPERATIONAL: Budget constraints may delay rollout schedules and limit deployment scope. STRATEGIC: Cost overruns may reduce funding available for future AI investments. COMPETITIVE: Delayed implementation may allow competitors to realize AI benefits sooner. | H6: 7 | I6: 2 | J6: =H6*I6 -> 14 | K6: M | L6: 1. Implement stage-gate project approvals. 2. Perform monthly budget reviews. 3. Establish contingency funding reserves. 4. Strengthen vendor contract governance. 5. Control project scope through formal change management. | M6: Chief Financial Officer/ Program Management Office | N6: Open
A7: R-006 | B7: Revenue Loss from AI Service Disruptions | C7: 46181 | D7: The risk that disruptions to AI-powered services negatively affect frontline operations and reduce sales revenue. | E7: This risk may be caused by cloud service outages, AI platform failures, software defects, integration issues, network disruptions, or failures in critical frontline AI applications. | F7: This may result in lost sales opportunities, reduced transaction volumes, customer dissatisfaction, and lower revenue growth. | G7: FINANCIAL: Revenue losses may occur due to service interruptions affecting store operations and customer transactions. OPERATIONAL: Store associates may be unable to access AI-powered tools needed for daily operations. REPUTATIONAL: Customers may experience service delays and reduced satisfaction. TECHNICAL: Increased pressure on IT teams to restore disrupted services. | H7: 5 | I7: 6 | J7: =H7*I7 -> 30 | K7: H | L7: 1. Establish cloud redundancy and failover capabilities. 2. Implement disaster recovery procedures. 3. Deploy real-time system monitoring. 4. Conduct regular resilience testing. 5. Maintain business continuity plans for critical operations. | M7: Chief Information Officer / Enterprise Technology Services | N7: Open
A8: R-007 | B8: Inventory Loss from AI Forecast Errors | C8: 46181 | D8: The risk that inaccurate AI forecasting models lead to inventory losses and inefficient inventory management decisions. | E8: This risk may be caused by poor data quality, changing consumer behavior, insufficient training data, demand volatility, or forecasting model limitations. | F8: This may result in excess inventory, stock shortages, inventory write-offs, increased carrying costs, and lost sales opportunities. | G8: FINANCIAL: Inventory losses may increase due to excess stock, markdowns, and inventory write-offs. OPERATIONAL: Poor forecasting may disrupt replenishment and inventory management processes. COMPETITIVE: Product availability issues may reduce customer satisfaction and competitiveness. STRATEGIC: Reduced confidence in AI-driven planning and forecasting capabilities. | H8: 7 | I8: 4 | J8: =H8*I8 -> 28 | K8: M | L8: 1. Continuously monitor forecast accuracy. 2. Implement human review of critical forecasts. 3. Retrain AI models regularly. 4. Maintain safety stock policies. 5. Conduct periodic data quality assessments. | M8: Chief Supply Chain Officer / Inventory Analytics Team | N8: Open
A9: R-008 | B9: Expected Labor Cost Reduction Not Achieved | C9: 46181 | D9: The risk that Walmart does not achieve the anticipated labor cost savings associated with Frontline AI Transformation. | E9: This risk may be caused by low AI adoption rates, inefficient workforce utilization, resistance to process changes, insufficient employee training, and the need to maintain additional staffing levels during the transition period. | F9: This may result in higher-than-expected labor expenses, reduced operational efficiency, and failure to achieve projected cost reduction targets. | G9: FINANCIAL: Expected labor savings may not materialize, reducing overall project value. OPERATIONAL: Workforce productivity improvements may be delayed. STRATEGIC: Reduced justification for future workforce automation initiatives. COMPETITIVE: Competitors achieving greater labor efficiency through AI may strengthen their cost advantage. | H9: 5 | I9: 1 | J9: =H9*I9 -> 5 | K9: L | L9: 1. Expand AI training and workforce enablement programs. 2. Monitor labor productivity KPIs. 3. Conduct regular workforce adoption assessments. 4. Align workforce incentives with AI adoption goals. 5. Continuously improve frontline AI workflows. | M9: Store Operations Leadership | N9: Open
A10: R-009 | B10: Inventory Forecast Error | C10: 46181 | D10: The risk that AI-powered inventory forecasting models generate inaccurate demand predictions for products across Walmart stores. | E10: This risk may be caused by poor data quality, rapidly changing customer purchasing behavior, seasonal demand fluctuations, incomplete historical data, and limitations in AI forecasting algorithms. | F10: This may result in inaccurate inventory planning, product shortages, excess inventory, inefficient replenishment decisions, and reduced customer satisfaction. | G10: FINANCIAL: Increased inventory carrying costs and lost sales opportunities. OPERATIONAL: Inventory imbalances affecting store operations and replenishment activities. CUSTOMER: Reduced product availability and customer satisfaction. COMPETITIVE: Lower service levels compared to competitors with more accurate forecasting capabilities. | H10: 7 | I10: 8 | J10: =H10*I10 -> 56 | K10: H | L10: 1. Continuously monitor forecast accuracy KPIs. 2. Retrain forecasting models regularly. 3. Establish human review for critical inventory categories. 4. Maintain safety stock thresholds. 5. Improve master data governance and inventory data quality. | M10: AI Analytics Team / Inventory Planning Department | N10: Open
A11: R-010 | B11: Stockout Risk | C11: 46181 | D11: The risk that products become unavailable to customers due to failures in AI-driven forecasting, replenishment, or inventory management processes. | E11: This risk may be caused by inaccurate demand forecasts, delayed replenishment activities, supplier disruptions, inventory visibility issues, or excessive dependence on automated decision-making. | F11: This may result in lost sales, dissatisfied customers, reduced customer loyalty, and lower store performance. | G11: FINANCIAL: Revenue loss from missed sales opportunities. OPERATIONAL: Reduced inventory availability across stores. CUSTOMER: Poor shopping experience and customer frustration. COMPETITIVE: Customers may switch to competitors with better product availability. | H11: 7 | I11: 8 | J11: =H11*I11 -> 56 | K11: H | L11: 1. Establish real-time inventory monitoring. 2. Implement automated stockout alerts. 3. Maintain safety stock levels. 4. Increase replenishment review frequency. 5. Improve supplier coordination processes. | M11: Inventory Management Department / Store Operations Leadership | N11: Open
A12: R-011 | B12: Overstock Risk | C12: 46181 | D12: The risk that AI forecasting models overestimate demand and create excessive inventory levels. | E12: This risk may be caused by inaccurate forecasting assumptions, poor data quality, unexpected demand changes, and model bias toward higher inventory recommendations. | F12: This may result in excess inventory accumulation, increased storage costs, markdowns, and inventory write-offs. | G12: FINANCIAL: Increased carrying costs and inventory markdown expenses. OPERATIONAL: Reduced warehouse and store storage efficiency. STRATEGIC: Reduced confidence in AI forecasting capabilities. | H12: 5 | I12: 6 | J12: =H12*I12 -> 30 | K12: M | L12: 1. Monitor inventory turnover metrics. 2. Conduct regular forecast validation reviews. 3. Implement dynamic inventory thresholds. 4. Improve demand sensing capabilities. 5. Strengthen inventory governance controls. | M12: Inventory Planning Team / Supply Chain Analytics Department | N12: Open
A13: R-012 | B13: Replenishment Delay | C13: 46181 | D13: The risk that AI-enabled replenishment processes fail to restock products in a timely manner. | E13: This risk may be caused by delayed inventory signals, inaccurate replenishment recommendations, supplier performance issues, transportation delays, and technology failures. | F13: This may result in empty shelves, stock shortages, delayed product availability, and reduced operational efficiency. | G13: FINANCIAL: Lost sales opportunities due to unavailable inventory. OPERATIONAL: Reduced replenishment efficiency and inventory performance. CUSTOMER: Negative shopping experience caused by empty shelves. | H13: 5 | I13: 6 | J13: =H13*I13 -> 30 | K13: M | L13: 1. Implement replenishment exception monitoring. 2. Improve supplier performance management. 3. Establish manual override procedures. 4. Increase visibility into inventory movement. 5. Conduct regular replenishment audits. | M13: Supply Chain Operations / Replenishment Management Team | N13: Open
A14: R-013 | B14: Fulfillment Disruption | C14: 46181 | D14: The risk that AI-related failures disrupt store fulfillment activities and customer order processing. | E14: This risk may be caused by AI system outages, inaccurate task prioritization, inventory visibility issues, labor shortages, and workflow automation failures. | F14: This may result in delayed order fulfillment, reduced order accuracy, customer dissatisfaction, and operational inefficiencies. | G14: FINANCIAL: Revenue loss from delayed or cancelled orders. OPERATIONAL: Reduced fulfillment efficiency and order accuracy. CUSTOMER: Lower customer satisfaction and trust. COMPETITIVE: Increased risk of customer migration to competitors. | H14: 7 | I14: 8 | J14: =H14*I14 -> 56 | K14: H | L14: 1. Implement fulfillment performance monitoring. 2. Maintain manual backup fulfillment processes. 3. Conduct operational resilience testing. 4. Improve inventory visibility across channels. 5. Strengthen workforce training and escalation procedures. | M14: Chief Operations Officer / Store Fulfillment Operations / E-Commerce Operations Team | N14: Open
A15: R-014 | B15: Incorrect Workforce Scheduling | C15: 46181 | D15: The risk that AI-powered workforce scheduling tools generate inefficient, inaccurate, or unfair employee schedules. | E15: This risk may be caused by inaccurate labor demand forecasts, incomplete employee availability data, scheduling algorithm limitations, insufficient consideration of local store conditions, and lack of managerial review of AI-generated schedules. | F15: This may result in staffing shortages, overstaffing, increased overtime costs, employee dissatisfaction, reduced productivity, and lower customer service quality. | G15: FINANCIAL: Increased labor costs due to overtime, scheduling inefficiencies, and workforce turnover. OPERATIONAL: Reduced staffing effectiveness and service coverage. REPUTATIONAL: Employee dissatisfaction may negatively impact Walmart's employer brand. LEGAL/COMPLIANCE: Potential labor compliance concerns regarding scheduling fairness and employee treatment. | H15: 5 | I15: 4 | J15: =H15*I15 -> 20 | K15: M | L15: 1. Require managerial approval of AI-generated schedules. 2. Conduct regular scheduling fairness reviews. 3. Continuously retrain scheduling algorithms. 4. Collect employee feedback on scheduling effectiveness. 5. Monitor overtime and labor utilization metrics. | M15: Store Operations Management / Workforce Planning Department | N15: Open
A16: R-015 | B16: Productivity Decline During Transition | C16: 46181 | D16: The risk that employee productivity temporarily declines during the implementation and adoption of AI-powered frontline tools. | E16: This risk may be caused by employee learning curves, unfamiliarity with AI systems, process changes, training requirements, and temporary disruptions to established workflows. | F16: This may result in reduced operational efficiency, slower task completion, lower service levels, and delayed realization of expected business benefits. | G16: FINANCIAL: Reduced productivity may increase labor costs during implementation. OPERATIONAL: Temporary reduction in store efficiency and performance. STRATEGIC: Delayed realization of AI transformation objectives. | H16: 7 | I16: 2 | J16: =H16*I16 -> 14 | K16: M | L16: 1. Develop structured AI training programs. 2. Implement phased deployment across stores. 3. Provide ongoing frontline support resources. 4. Establish change management communication plans. 5. Monitor productivity KPIs throughout implementation. | M16: Store Operations Leadership / Learning & Development Department | N16: Open
... A31: R-030 | B31: Algorithmic Bias & Ethical AI Issues | C31: 46181 | D31: The risk that AI systems generate unfair, discriminatory, or biased outcomes affecting customers, employees, or business decisions. | E31: This risk may be caused by biased training data, inadequate model testing, lack of diversity in data sources, insufficient governance oversight, and limitations in AI model design. | F31: This may result in unfair workforce scheduling decisions, unequal customer treatment, discrimination claims, regulatory scrutiny, and reputational damage. | G31: LEGAL/COMPLIANCE: Potential discrimination claims and regulatory investigations. REPUTATIONAL: Public criticism regarding AI fairness and ethics. OPERATIONAL: Reduced confidence in AI-supported decision making. STRATEGIC: Increased restrictions on AI deployment and adoption. | H31: 3 | I31: 4 | J31: =H31*I31 -> 12 | K31: L | L31: Conduct bias testing before deployment. Implement Responsible AI governance standards. Establish independent AI review processes. Maintain human oversight for high-impact decisions. Perform periodic fairness assessments and audits. | M31: Chief Compliance Officer AI Governance Committee | N31: Open

Sheet Risk Register
A1: Risk # | B1: The Risk of/That | C1: Likelihood Score | D1: Impact Score | E1: Risk Score | F1: Priority | H1: Impact / Likelihood | I1: 1 | J1: 3 | K1: 5 | L1: 7 | M1: 9
A2: R1 | B2: Competitive AI Disruption | C2: 3 | D2: 8 | E2: =C2*D2 -> 24 | F2: =IF(E2>=40,"H",IF(E2>=15,"M","L")) -> M | H2: 9 | I2: =I$1*$H2 -> 9 | J2: =J$1*$H2 -> 27 | K2: =K$1*$H2 -> 45 | L2: =L$1*$H2 -> 63 | M2: =M$1*$H2 -> 81
A3: R2 | B3: Customer Migration Risk | C3: 5 | D3: 6 | E3: =C3*D3 -> 30 | F3: =IF(E3>=40,"H",IF(E3>=15,"M","L")) -> M | H3: 8 | I3: =I$1*$H3 -> 8 | J3: =J$1*$H3 -> 24 | K3: =K$1*$H3 -> 40 | L3: =L$1*$H3 -> 56 | M3: =M$1*$H3 -> 72
A4: R3 | B4: AI-Driven Supply Chain Optimization and Cost Leadership Risk | C4: 5 | D4: 4 | E4: =C4*D4 -> 20 | F4: =IF(E4>=40,"H",IF(E4>=15,"M","L")) -> M | H4: 6 | I4: =I$1*$H4 -> 6 | J4: =J$1*$H4 -> 18 | K4: =K$1*$H4 -> 30 | L4: =L$1*$H4 -> 42 | M4: =M$1*$H4 -> 54
A5: R4 | B5: ROI realization failure | C5: 5 | D5: 8 | E5: =C5*D5 -> 40 | F5: =IF(E5>=40,"H",IF(E5>=15,"M","L")) -> H | H5: 4 | I5: =I$1*$H5 -> 4 | J5: =J$1*$H5 -> 12 | K5: =K$1*$H5 -> 20 | L5: =L$1*$H5 -> 28 | M5: =M$1*$H5 -> 36
A6: R5 | B6: AI Implementation Cost Overrun | C6: 7 | D6: 2 | E6: =C6*D6 -> 14 | F6: =IF(E6>=40,"H",IF(E6>=15,"M","L")) -> L | H6: 2 | I6: =I$1*$H6 -> 2 | J6: =J$1*$H6 -> 6 | K6: =K$1*$H6 -> 10 | L6: =L$1*$H6 -> 14 | M6: =M$1*$H6 -> 18
A7: R6 | B7: Revenue Loss from AI Service Disruptions | C7: 5 | D7: 6 | E7: =C7*D7 -> 30 | F7: =IF(E7>=40,"H",IF(E7>=15,"M","L")) -> M | H7: 1 | I7: =I$1*$H7 -> 1 | J7: =J$1*$H7 -> 3 | K7: =K$1*$H7 -> 5 | L7: =L$1*$H7 -> 7 | M7: =M$1*$H7 -> 9
A8: R7 | B8: Inventory Loss from AI Forecast Errors | C8: 7 | D8: 4 | E8: =C8*D8 -> 28 | F8: =IF(E8>=40,"H",IF(E8>=15,"M","L")) -> M
A9: R8 | B9: Expected Labor Cost Reduction Not Achieved | C9: 5 | D9: 1 | E9: =C9*D9 -> 5 | F9: =IF(E9>=40,"H",IF(E9>=15,"M","L")) -> L
A10: R9 | B10: Inventory Forecast Error | C10: 7 | D10: 8 | E10: =C10*D10 -> 56 | F10: =IF(E10>=40,"H",IF(E10>=15,"M","L")) -> H | H10: Low risk | I10: 1~14
A11: R10 | B11: Stockout Risk | C11: 7 | D11: 8 | E11: =C11*D11 -> 56 | F11: =IF(E11>=40,"H",IF(E11>=15,"M","L")) -> H | H11: Medium risk | I11: 15~39
A12: R11 | B12: Overstock Risk | C12: 5 | D12: 6 | E12: =C12*D12 -> 30 | F12: =IF(E12>=40,"H",IF(E12>=15,"M","L")) -> M | H12: High risk | I12: 40~81
A13: R12 | B13: Replenishment Delay | C13: 5 | D13: 6 | E13: =C13*D13 -> 30 | F13: =IF(E13>=40,"H",IF(E13>=15,"M","L")) -> M
A14: R13 | B14: Fulfillment Disruption | C14: 7 | D14: 8 | E14: =C14*D14 -> 56 | F14: =IF(E14>=40,"H",IF(E14>=15,"M","L")) -> H
A15: R14 | B15: Incorrect Workforce Scheduling | C15: 5 | D15: 4 | E15: =C15*D15 -> 20 | F15: =IF(E15>=40,"H",IF(E15>=15,"M","L")) -> M
A16: R15 | B16: Productivity Decline During Transition | C16: 7 | D16: 2 | E16: =C16*D16 -> 14 | F16: =IF(E16>=40,"H",IF(E16>=15,"M","L")) -> L
A17: R16 | B17: Poor Data Quality | C17: 7 | D17: 4 | E17: =C17*D17 -> 28 | F17: =IF(E17>=40,"H",IF(E17>=15,"M","L")) -> M
A18: R17 | B18: Operational Decision Errors | C18: 5 | D18: 4 | E18: =C18*D18 -> 20 | F18: =IF(E18>=40,"H",IF(E18>=15,"M","L")) -> M
A19: R18 | B19: Excessive Dependence on Automation | C19: 5 | D19: 6 | E19: =C19*D19 -> 30 | F19: =IF(E19>=40,"H",IF(E19>=15,"M","L")) -> M
A20: R19 | B20: Customer Trust Erosion | C20: 5 | D20: 6 | E20: =C20*D20 -> 30 | F20: =IF(E20>=40,"H",IF(E20>=15,"M","L")) -> M
A21: R20 | B21: Negative Public Perception of AI | C21: 5 | D21: 4 | E21: =C21*D21 -> 20 | F21: =IF(E21>=40,"H",IF(E21>=15,"M","L")) -> M
A22: R21 | B22: AI-Related Customer Complaints | C22: 7 | D22: 2 | E22: =C22*D22 -> 14 | F22: =IF(E22>=40,"H",IF(E22>=15,"M","L")) -> L
A23: R22 | B23: Brand Damage from AI Failures | C23: 3 | D23: 8 | E23: =C23*D23 -> 24 | F23: =IF(E23>=40,"H",IF(E23>=15,"M","L")) -> M
A24: R23 | B24: AI Recommendation Inaccuracy | C24: 5 | D24: 4 | E24: =C24*D24 -> 20 | F24: =IF(E24>=40,"H",IF(E24>=15,"M","L")) -> M
... A31: R30 | B31: Algorithmic Bias & Ethical AI Issues | C31: 3 | D31: 4 | E31: =C31*D31 -> 12 | F31: =IF(E31>=40,"H",IF(E31>=15,"M","L")) -> L

Sheet HeatMap Excel
A1: Walmart Frontline AI Transformation Risk Heat Map
A2: Impact / Likelihood | B2: 1 | C2: 3 | D2: 5 | E2: 7 | F2: 9
A3: 9 | B3: {=_xlfn.TEXTJOIN(", ",TRUE,_xlfn._xlws.FILTER('Risk Register'!$A$2:$A$31,('Risk Register'!$C$2:$C$31=B$2)*('Risk Register'!$D$2:$D$31=$A3),""))} | C3: {=_xlfn.TEXTJOIN(", ",TRUE,_xlfn._xlws.FILTER('Risk Register'!$A$2:$A$31,('Risk Register'!$C$2:$C$31=C$2)*('Risk Register'!$D$2:$D$31=$A3),""))} | D3: {=_xlfn.TEXTJOIN(", ",TRUE,_xlfn._xlws.FILTER('Risk Register'!$A$2:$A$31,('Risk Register'!$C$2:$C$31=D$2)*('Risk Register'!$D$2:$D$31=$A3),""))} | E3: {=_xlfn.TEXTJOIN(", ",TRUE,_xlfn._xlws.FILTER('Risk Register'!$A$2:$A$31,('Risk Register'!$C$2:$C$31=E$2)*('Risk Register'!$D$2:$D$31=$A3),""))} | F3: {=_xlfn.TEXTJOIN(", ",TRUE,_xlfn._xlws.FILTER('Risk Register'!$A$2:$A$31,('Risk Register'!$C$2:$C$31=F$2)*('Risk Register'!$D$2:$D$31=$A3),""))}
A4: 8 | B4: {=_xlfn.TEXTJOIN(", ",TRUE,_xlfn._xlws.FILTER('Risk Register'!$A$2:$A$31,('Risk Register'!$C$2:$C$31=B$2)*('Risk Register'!$D$2:$D$31=$A4),""))} | C4: {=_xlfn.TEXTJOIN(", ",TRUE,_xlfn._xlws.FILTER('Risk Register'!$A$2:$A$31,('Risk Register'!$C$2:$C$31=C$2)*('Risk Register'!$D$2:$D$31=$A4),""))} -> R1, R22 | D4: {=_xlfn.TEXTJOIN(", ",TRUE,_xlfn._xlws.FILTER('Risk Register'!$A$2:$A$31,('Risk Register'!$C$2:$C$31=D$2)*('Risk Register'!$D$2:$D$31=$A4),""))} -> R4, R25, R28 | E4: {=_xlfn.TEXTJOIN(", ",TRUE,_xlfn._xlws.FILTER('Risk Register'!$A$2:$A$31,('Risk Register'!$C$2:$C$31=E$2)*('Risk Register'!$D$2:$D$31=$A4),""))} -> R9, R10, R13 | F4: {=_xlfn.TEXTJOIN(", ",TRUE,_xlfn._xlws.FILTER('Risk Register'!$A$2:$A$31,('Risk Register'!$C$2:$C$31=F$2)*('Risk Register'!$D$2:$D$31=$A4),""))}
A5: 6 | B5: {=_xlfn.TEXTJOIN(", ",TRUE,_xlfn._xlws.FILTER('Risk Register'!$A$2:$A$31,('Risk Register'!$C$2:$C$31=B$2)*('Risk Register'!$D$2:$D$31=$A5),""))} | C5: {=_xlfn.TEXTJOIN(", ",TRUE,_xlfn._xlws.FILTER('Risk Register'!$A$2:$A$31,('Risk Register'!$C$2:$C$31=C$2)*('Risk Register'!$D$2:$D$31=$A5),""))} | D5: {=_xlfn.TEXTJOIN(", ",TRUE,_xlfn._xlws.FILTER('Risk Register'!$A$2:$A$31,('Risk Register'!$C$2:$C$31=D$2)*('Risk Register'!$D$2:$D$31=$A5),""))} -> R2, R6, R11, R12, R18, R19, R29 | E5: {=_xlfn.TEXTJOIN(", ",TRUE,_xlfn._xlws.FILTER('Risk Register'!$A$2:$A$31,('Risk Register'!$C$2:$C$31=E$2)*('Risk Register'!$D$2:$D$31=$A5),""))} -> R26, R27 | F5: {=_xlfn.TEXTJOIN(", ",TRUE,_xlfn._xlws.FILTER('Risk Register'!$A$2:$A$31,('Risk Register'!$C$2:$C$31=F$2)*('Risk Register'!$D$2:$D$31=$A5),""))}
A6: 4 | B6: {=_xlfn.TEXTJOIN(", ",TRUE,_xlfn._xlws.FILTER('Risk Register'!$A$2:$A$31,('Risk Register'!$C$2:$C$31=B$2)*('Risk Register'!$D$2:$D$31=$A6),""))} | C6: {=_xlfn.TEXTJOIN(", ",TRUE,_xlfn._xlws.FILTER('Risk Register'!$A$2:$A$31,('Risk Register'!$C$2:$C$31=C$2)*('Risk Register'!$D$2:$D$31=$A6),""))} -> R30 | D6: {=_xlfn.TEXTJOIN(", ",TRUE,_xlfn._xlws.FILTER('Risk Register'!$A$2:$A$31,('Risk Register'!$C$2:$C$31=D$2)*('Risk Register'!$D$2:$D$31=$A6),""))} -> R3, R14, R17, R20, R23 | E6: {=_xlfn.TEXTJOIN(", ",TRUE,_xlfn._xlws.FILTER('Risk Register'!$A$2:$A$31,('Risk Register'!$C$2:$C$31=E$2)*('Risk Register'!$D$2:$D$31=$A6),""))} -> R7, R16 | F6: {=_xlfn.TEXTJOIN(", ",TRUE,_xlfn._xlws.FILTER('Risk Register'!$A$2:$A$31,('Risk Register'!$C$2:$C$31=F$2)*('Risk Register'!$D$2:$D$31=$A6),""))}
A7: 2 | B7: {=_xlfn.TEXTJOIN(", ",TRUE,_xlfn._xlws.FILTER('Risk Register'!$A$2:$A$31,('Risk Register'!$C$2:$C$31=B$2)*('Risk Register'!$D$2:$D$31=$A7),""))} | C7: {=_xlfn.TEXTJOIN(", ",TRUE,_xlfn._xlws.FILTER('Risk Register'!$A$2:$A$31,('Risk Register'!$C$2:$C$31=C$2)*('Risk Register'!$D$2:$D$31=$A7),""))} | D7: {=_xlfn.TEXTJOIN(", ",TRUE,_xlfn._xlws.FILTER('Risk Register'!$A$2:$A$31,('Risk Register'!$C$2:$C$31=D$2)*('Risk Register'!$D$2:$D$31=$A7),""))} | E7: {=_xlfn.TEXTJOIN(", ",TRUE,_xlfn._xlws.FILTER('Risk Register'!$A$2:$A$31,('Risk Register'!$C$2:$C$31=E$2)*('Risk Register'!$D$2:$D$31=$A7),""))} -> R5, R15, R21, R24 | F7: {=_xlfn.TEXTJOIN(", ",TRUE,_xlfn._xlws.FILTER('Risk Register'!$A$2:$A$31,('Risk Register'!$C$2:$C$31=F$2)*('Risk Register'!$D$2:$D$31=$A7),""))}
A8: 1 | B8: {=_xlfn.TEXTJOIN(", ",TRUE,_xlfn._xlws.FILTER('Risk Register'!$A$2:$A$31,('Risk Register'!$C$2:$C$31=B$2)*('Risk Register'!$D$2:$D$31=$A8),""))} | C8: {=_xlfn.TEXTJOIN(", ",TRUE,_xlfn._xlws.FILTER('Risk Register'!$A$2:$A$31,('Risk Register'!$C$2:$C$31=C$2)*('Risk Register'!$D$2:$D$31=$A8),""))} | D8: {=_xlfn.TEXTJOIN(", ",TRUE,_xlfn._xlws.FILTER('Risk Register'!$A$2:$A$31,('Risk Register'!$C$2:$C$31=D$2)*('Risk Register'!$D$2:$D$31=$A8),""))} -> R8 | E8: {=_xlfn.TEXTJOIN(", ",TRUE,_xlfn._xlws.FILTER('Risk Register'!$A$2:$A$31,('Risk Register'!$C$2:$C$31=E$2)*('Risk Register'!$D$2:$D$31=$A8),""))} | F8: {=_xlfn.TEXTJOIN(", ",TRUE,_xlfn._xlws.FILTER('Risk Register'!$A$2:$A$31,('Risk Register'!$C$2:$C$31=F$2)*('Risk Register'!$D$2:$D$31=$A8),""))}
A10: Risk Threshold Definition
A11: Risk Level | B11: Score Range | C11: Color
A12: Low risk | B12: 1~14
A13: Medium risk | B13: 15~39
A14: High risk | B14: 40~81
A17: Risk # | B17: The Risk of/That | C17: Likelihood Score | D17: Impact Score | E17: Risk Score | F17: Priority
A18: R1 | B18: Competitive AI Disruption | C18: 3 | D18: 8 | E18: =C18*D18 -> 24 | F18: =IF(E18>=40,"H",IF(E18>=15,"M","L")) -> M
A19: R2 | B19: Customer Migration Risk | C19: 5 | D19: 6 | E19: =C19*D19 -> 30 | F19: =IF(E19>=40,"H",IF(E19>=15,"M","L")) -> M
A20: R3 | B20: AI-Driven Supply Chain Optimization and Cost Leadership Risk | C20: 5 | D20: 4 | E20: =C20*D20 -> 20 | F20: =IF(E20>=40,"H",IF(E20>=15,"M","L")) -> M
A21: R4 | B21: ROI realization failure | C21: 5 | D21: 8 | E21: =C21*D21 -> 40 | F21: =IF(E21>=40,"H",IF(E21>=15,"M","L")) -> H
A22: R5 | B22: AI Implementation Cost Overrun | C22: 7 | D22: 2 | E22: =C22*D22 -> 14 | F22: =IF(E22>=40,"H",IF(E22>=15,"M","L")) -> L
A23: R6 | B23: Revenue Loss from AI Service Disruptions | C23: 5 | D23: 6 | E23: =C23*D23 -> 30 | F23: =IF(E23>=40,"H",IF(E23>=15,"M","L")) -> M
A24: R7 | B24: Inventory Loss from AI Forecast Errors | C24: 7 | D24: 4 | E24: =C24*D24 -> 28 | F24: =IF(E24>=40,"H",IF(E24>=15,"M","L")) -> M
A25: R8 | B25: Expected Labor Cost Reduction Not Achieved | C25: 5 | D25: 1 | E25: =C25*D25 -> 5 | F25: =IF(E25>=40,"H",IF(E25>=15,"M","L")) -> L
A26: R9 | B26: Inventory Forecast Error | C26: 7 | D26: 8 | E26: =C26*D26 -> 56 | F26: =IF(E26>=40,"H",IF(E26>=15,"M","L")) -> H
A27: R10 | B27: Stockout Risk | C27: 7 | D27: 8 | E27: =C27*D27 -> 56 | F27: =IF(E27>=40,"H",IF(E27>=15,"M","L")) -> H
A28: R11 | B28: Overstock Risk | C28: 5 | D28: 6 | E28: =C28*D28 -> 30 | F28: =IF(E28>=40,"H",IF(E28>=15,"M","L")) -> M
A29: R12 | B29: Replenishment Delay | C29: 5 | D29: 6 | E29: =C29*D29 -> 30 | F29: =IF(E29>=40,"H",IF(E29>=15,"M","L")) -> M
... A47: R30 | B47: Algorithmic Bias & Ethical AI Issues | C47: 3 | D47: 4 | E47: =C47*D47 -> 12 | F47: =IF(E47>=40,"H",IF(E47>=15,"M","L")) -> L

Sheet HeatMap Python
A37: Risk Heat Map Interpretation: The risk heat map illustrates the distribution of identified risks based on their likelihood and impact scores. The horizontal axis represents the likelihood of occurrence, while the vertical axis represents the potential business impact. Each risk was positioned according to its assessed likelihood and impact score, and the color gradient reflects the corresponding total risk score (Likelihood × Impact). The heat map indicates that the highest-priority risks are concentrated in the upper-right region of the matrix, where both likelihood and impact are elevated. Key risks within this area include Inventory Forecast Error (R9), Stockout Risk (R10), Fulfillment Disruption (R13), Legacy System Integration Failure (R26), Vendor Dependency (R27), Customer Data Breach (R28), ROI Realization Failure (R4), and System Downtime (R25). These risks have the greatest potential to affect Walmart’s frontline AI transformation and therefore require the highest level of management attention and mitigation planning. Lower-priority risks such as Expected Labor Cost Reduction Not Achieved (R8) and Algorithmic Bias & Ethical AI Issues (R30) are positioned in the lower-left portion of the matrix, indicating relatively lower business impact and/or likelihood.
A95: Risk Score Ranking Interpretation: The risk score ranking chart presents all identified risks in descending order based on their total risk scores, calculated as the product of likelihood and impact. This visualization supports management prioritization by clearly identifying which risks pose the greatest threat to the successful implementation of Walmart’s frontline AI transformation initiatives. The results show that Inventory Forecast Error (R9), Stockout Risk (R10), and Fulfillment Disruption (R13) are the highest-ranked risks, each receiving a total risk score of 56. These are followed by Legacy System Integration Failure (R26) and Vendor Dependency (R27), both with scores of 42, and Customer Data Breach (R28), ROI Realization Failure (R4), and System Downtime (R25), each with scores of 40. These risks represent the most significant operational, technical, and strategic concerns and should be prioritized for monitoring, mitigation, and executive oversight. In contrast, lower-ranked risks such as Expected Labor Cost Reduction Not Achieved (R8) and Algorithmic Bias & Ethical AI Issues (R30) have comparatively lower risk scores and may require less immediate management attention.
A109: Risk Threshold Definition
A110: Risk Level | B110: Score Range | C110: Color
A111: Low risk | B111: 1~14
A112: Medium risk | B112: 15~39
A113: High risk | B113: 40~81
A115: These thresholds were consistently applied throughout both the Excel and Python heat maps. Risks classified as High Risk require immediate management attention and active mitigation strategies. Medium Risk items should be monitored and managed through appropriate controls, while Low Risk items may be accepted, monitored periodically, or addressed through routine operational management processes.
